{
  "generated_at": "2026-05-24T08:30:10.861443+00:00",
  "region": "GMS (North America)",
  "thresholds": [
    270,
    275,
    280,
    285,
    290,
    295,
    300
  ],
  "min_level": 270,
  "classes": {
    "Adele": {
      "270": 3450,
      "275": 3450,
      "280": 3450,
      "285": 3450,
      "290": 3450,
      "295": 735,
      "300": 0
    },
    "Angelic Buster": {
      "270": 6200,
      "275": 6200,
      "280": 6200,
      "285": 5675,
      "290": 2315,
      "295": 205,
      "300": 1
    },
    "Aran": {
      "270": 6100,
      "275": 6100,
      "280": 6100,
      "285": 5055,
      "290": 2095,
      "295": 145,
      "300": 1
    },
    "Arch Mage (F/P)": {
      "270": 3500,
      "275": 3500,
      "280": 3500,
      "285": 3500,
      "290": 1955,
      "295": 145,
      "300": 0
    },
    "Arch Mage (I/L)": {
      "270": 5300,
      "275": 5300,
      "280": 5300,
      "285": 5300,
      "290": 2715,
      "295": 355,
      "300": 1
    },
    "Ark": {
      "270": 5500,
      "275": 5500,
      "280": 5500,
      "285": 3765,
      "290": 1745,
      "295": 95,
      "300": 0
    },
    "Battle Mage": {
      "270": 6050,
      "275": 6050,
      "280": 6050,
      "285": 4725,
      "290": 1795,
      "295": 85,
      "300": 3
    },
    "Bishop": {
      "270": 5400,
      "275": 5400,
      "280": 5400,
      "285": 5400,
      "290": 5400,
      "295": 1295,
      "300": 6
    },
    "Blade Master": {
      "270": 5600,
      "275": 5600,
      "280": 5600,
      "285": 5600,
      "290": 4255,
      "295": 455,
      "300": 1
    },
    "Blaster": {
      "270": 6000,
      "275": 5655,
      "280": 3625,
      "285": 2155,
      "290": 865,
      "295": 28,
      "300": 1
    },
    "Blaze Wizard": {
      "270": 5850,
      "275": 4025,
      "280": 1875,
      "285": 805,
      "290": 315,
      "295": 6,
      "300": 0
    },
    "Bow Master": {
      "270": 5900,
      "275": 5900,
      "280": 5900,
      "285": 5900,
      "290": 4315,
      "295": 345,
      "300": 1
    },
    "Buccaneer": {
      "270": 5700,
      "275": 5700,
      "280": 5700,
      "285": 5700,
      "290": 4805,
      "295": 385,
      "300": 3
    },
    "Cadena": {
      "270": 5150,
      "275": 5150,
      "280": 5150,
      "285": 4255,
      "290": 1725,
      "295": 45,
      "300": 0
    },
    "Corsair": {
      "270": 6100,
      "275": 6100,
      "280": 6100,
      "285": 3375,
      "290": 1195,
      "295": 65,
      "300": 0
    },
    "Dark Knight": {
      "270": 5850,
      "275": 5850,
      "280": 5850,
      "285": 4965,
      "290": 1875,
      "295": 195,
      "300": 0
    },
    "Dawn Warrior": {
      "270": 5850,
      "275": 5850,
      "280": 5850,
      "285": 5850,
      "290": 5625,
      "295": 405,
      "300": 0
    },
    "Demon Avenger": {
      "270": 6100,
      "275": 6100,
      "280": 6079,
      "285": 2775,
      "290": 1255,
      "295": 135,
      "300": 0
    },
    "Demon Slayer": {
      "270": 5450,
      "275": 5450,
      "280": 5450,
      "285": 5450,
      "290": 5450,
      "295": 655,
      "300": 1
    },
    "Evan": {
      "270": 6300,
      "275": 6300,
      "280": 5875,
      "285": 3335,
      "290": 1455,
      "295": 85,
      "300": 1
    },
    "Hayato": {
      "270": 6350,
      "275": 6350,
      "280": 6350,
      "285": 5325,
      "290": 1935,
      "295": 145,
      "300": 1
    },
    "Hero": {
      "270": 5950,
      "275": 5950,
      "280": 5950,
      "285": 5950,
      "290": 5950,
      "295": 865,
      "300": 6
    },
    "Hoyoung": {
      "270": 5850,
      "275": 5850,
      "280": 5850,
      "285": 5850,
      "290": 3145,
      "295": 355,
      "300": 3
    },
    "Illium": {
      "270": 5950,
      "275": 5950,
      "280": 5950,
      "285": 3995,
      "290": 1485,
      "295": 45,
      "300": 0
    },
    "Kain": {
      "270": 6150,
      "275": 6150,
      "280": 6150,
      "285": 3685,
      "290": 1645,
      "295": 145,
      "300": 0
    },
    "Kaiser": {
      "270": 5750,
      "275": 5750,
      "280": 5695,
      "285": 2905,
      "290": 1145,
      "295": 145,
      "300": 3
    },
    "Kanna": {
      "270": 5750,
      "275": 5750,
      "280": 5750,
      "285": 5750,
      "290": 2855,
      "295": 305,
      "300": 1
    },
    "Khali": {
      "270": 6200,
      "275": 6200,
      "280": 6200,
      "285": 3335,
      "290": 1175,
      "295": 55,
      "300": 0
    },
    "Kinesis": {
      "270": 5700,
      "275": 5335,
      "280": 3415,
      "285": 1945,
      "290": 905,
      "295": 15,
      "300": 0
    },
    "Lara": {
      "270": 6100,
      "275": 6100,
      "280": 5725,
      "285": 3055,
      "290": 1305,
      "295": 125,
      "300": 0
    },
    "Luminous": {
      "270": 5800,
      "275": 5800,
      "280": 5800,
      "285": 4385,
      "290": 1845,
      "295": 245,
      "300": 0
    },
    "Marksman": {
      "270": 6100,
      "275": 6100,
      "280": 6100,
      "285": 3765,
      "290": 1615,
      "295": 165,
      "300": 0
    },
    "Mechanic": {
      "270": 5800,
      "275": 5185,
      "280": 2835,
      "285": 1355,
      "290": 525,
      "295": 10,
      "300": 0
    },
    "Mercedes": {
      "270": 5600,
      "275": 5600,
      "280": 5600,
      "285": 5600,
      "290": 2925,
      "295": 205,
      "300": 0
    },
    "Mihile": {
      "270": 6000,
      "275": 6000,
      "280": 6000,
      "285": 3385,
      "290": 1355,
      "295": 36,
      "300": 0
    },
    "Night Lord": {
      "270": 5800,
      "275": 5800,
      "280": 5800,
      "285": 5800,
      "290": 5800,
      "295": 2105,
      "300": 45
    },
    "Night Walker": {
      "270": 5950,
      "275": 5950,
      "280": 5950,
      "285": 5950,
      "290": 5950,
      "295": 1045,
      "300": 1
    },
    "Paladin": {
      "270": 6150,
      "275": 6150,
      "280": 6150,
      "285": 5115,
      "290": 2015,
      "295": 115,
      "300": 0
    },
    "Pathfinder": {
      "270": 6100,
      "275": 6100,
      "280": 6100,
      "285": 5655,
      "290": 2465,
      "295": 255,
      "300": 0
    },
    "Phantom": {
      "270": 6000,
      "275": 6000,
      "280": 6000,
      "285": 4875,
      "290": 1985,
      "295": 185,
      "300": 0
    },
    "Shade": {
      "270": 5950,
      "275": 5950,
      "280": 5950,
      "285": 5135,
      "290": 1975,
      "295": 185,
      "300": 1
    },
    "Shadower": {
      "270": 6100,
      "275": 6100,
      "280": 6100,
      "285": 6100,
      "290": 6100,
      "295": 1035,
      "300": 1
    },
    "Thunder Breaker": {
      "270": 5800,
      "275": 5800,
      "280": 5800,
      "285": 2525,
      "290": 965,
      "295": 28,
      "300": 0
    },
    "Wild Hunter": {
      "270": 5850,
      "275": 5850,
      "280": 3505,
      "285": 1625,
      "290": 705,
      "295": 65,
      "300": 3
    },
    "Wind Archer": {
      "270": 6150,
      "275": 6150,
      "280": 6150,
      "285": 6150,
      "290": 2595,
      "295": 185,
      "300": 0
    },
    "Xenon": {
      "270": 5750,
      "275": 5750,
      "280": 5750,
      "285": 5750,
      "290": 2915,
      "295": 345,
      "300": 1
    },
    "Zero": {
      "270": 5950,
      "275": 5950,
      "280": 5950,
      "285": 5950,
      "290": 2835,
      "295": 215,
      "300": 0
    }
  },
  "statuses": {
    "Adele": {
      "status": "blocked",
      "seen": 3450,
      "total_count": 266747,
      "stopped_at_page": 346
    },
    "Angelic Buster": {
      "status": "blocked",
      "seen": 6200,
      "total_count": 334314,
      "stopped_at_page": 621
    },
    "Aran": {
      "status": "blocked",
      "seen": 6100,
      "total_count": 451296,
      "stopped_at_page": 611
    },
    "Arch Mage (F/P)": {
      "status": "blocked",
      "seen": 3500,
      "total_count": 162157,
      "stopped_at_page": 351
    },
    "Arch Mage (I/L)": {
      "status": "blocked",
      "seen": 5300,
      "total_count": 249948,
      "stopped_at_page": 531
    },
    "Ark": {
      "status": "blocked",
      "seen": 5500,
      "total_count": 279284,
      "stopped_at_page": 551
    },
    "Battle Mage": {
      "status": "blocked",
      "seen": 6050,
      "total_count": 254515,
      "stopped_at_page": 606
    },
    "Bishop": {
      "status": "blocked",
      "seen": 5400,
      "total_count": 272907,
      "stopped_at_page": 541
    },
    "Blade Master": {
      "status": "blocked",
      "seen": 5600,
      "total_count": 235022,
      "stopped_at_page": 561
    },
    "Blaster": {
      "status": "blocked",
      "seen": 6000,
      "total_count": 169516,
      "stopped_at_page": 601
    },
    "Blaze Wizard": {
      "status": "blocked",
      "seen": 5850,
      "total_count": 267983,
      "stopped_at_page": 586
    },
    "Bow Master": {
      "status": "blocked",
      "seen": 5900,
      "total_count": 185623,
      "stopped_at_page": 591
    },
    "Buccaneer": {
      "status": "blocked",
      "seen": 5700,
      "total_count": 169871,
      "stopped_at_page": 571
    },
    "Cadena": {
      "status": "blocked",
      "seen": 5150,
      "total_count": 197544,
      "stopped_at_page": 516
    },
    "Corsair": {
      "status": "blocked",
      "seen": 6100,
      "total_count": 126211,
      "stopped_at_page": 611
    },
    "Dark Knight": {
      "status": "blocked",
      "seen": 5850,
      "total_count": 174102,
      "stopped_at_page": 586
    },
    "Dawn Warrior": {
      "status": "blocked",
      "seen": 5850,
      "total_count": 296540,
      "stopped_at_page": 586
    },
    "Demon Avenger": {
      "status": "blocked",
      "seen": 6100,
      "total_count": 412158,
      "stopped_at_page": 611
    },
    "Demon Slayer": {
      "status": "blocked",
      "seen": 5450,
      "total_count": 648185,
      "stopped_at_page": 546
    },
    "Evan": {
      "status": "blocked",
      "seen": 6300,
      "total_count": 392806,
      "stopped_at_page": 631
    },
    "Hayato": {
      "status": "blocked",
      "seen": 6350,
      "total_count": 435859,
      "stopped_at_page": 636
    },
    "Hero": {
      "status": "blocked",
      "seen": 5950,
      "total_count": 226285,
      "stopped_at_page": 596
    },
    "Hoyoung": {
      "status": "blocked",
      "seen": 5850,
      "total_count": 230430,
      "stopped_at_page": 586
    },
    "Illium": {
      "status": "blocked",
      "seen": 5950,
      "total_count": 174735,
      "stopped_at_page": 596
    },
    "Kain": {
      "status": "blocked",
      "seen": 6150,
      "total_count": 191046,
      "stopped_at_page": 616
    },
    "Kaiser": {
      "status": "blocked",
      "seen": 5750,
      "total_count": 345812,
      "stopped_at_page": 576
    },
    "Kanna": {
      "status": "blocked",
      "seen": 5750,
      "total_count": 1297760,
      "stopped_at_page": 576
    },
    "Khali": {
      "status": "blocked",
      "seen": 6200,
      "total_count": 150414,
      "stopped_at_page": 621
    },
    "Kinesis": {
      "status": "blocked",
      "seen": 5700,
      "total_count": 299503,
      "stopped_at_page": 571
    },
    "Lara": {
      "status": "blocked",
      "seen": 6100,
      "total_count": 210667,
      "stopped_at_page": 611
    },
    "Luminous": {
      "status": "blocked",
      "seen": 5800,
      "total_count": 566510,
      "stopped_at_page": 581
    },
    "Marksman": {
      "status": "blocked",
      "seen": 6100,
      "total_count": 159673,
      "stopped_at_page": 611
    },
    "Mechanic": {
      "status": "blocked",
      "seen": 5800,
      "total_count": 260176,
      "stopped_at_page": 581
    },
    "Mercedes": {
      "status": "blocked",
      "seen": 5600,
      "total_count": 619473,
      "stopped_at_page": 561
    },
    "Mihile": {
      "status": "blocked",
      "seen": 6000,
      "total_count": 173255,
      "stopped_at_page": 601
    },
    "Night Lord": {
      "status": "blocked",
      "seen": 5800,
      "total_count": 273996,
      "stopped_at_page": 581
    },
    "Night Walker": {
      "status": "blocked",
      "seen": 5950,
      "total_count": 301812,
      "stopped_at_page": 596
    },
    "Paladin": {
      "status": "blocked",
      "seen": 6150,
      "total_count": 126371,
      "stopped_at_page": 616
    },
    "Pathfinder": {
      "status": "blocked",
      "seen": 6100,
      "total_count": 182016,
      "stopped_at_page": 611
    },
    "Phantom": {
      "status": "blocked",
      "seen": 6000,
      "total_count": 422316,
      "stopped_at_page": 601
    },
    "Shade": {
      "status": "blocked",
      "seen": 5950,
      "total_count": 313310,
      "stopped_at_page": 596
    },
    "Shadower": {
      "status": "blocked",
      "seen": 6100,
      "total_count": 210188,
      "stopped_at_page": 611
    },
    "Thunder Breaker": {
      "status": "blocked",
      "seen": 5800,
      "total_count": 218065,
      "stopped_at_page": 581
    },
    "Wild Hunter": {
      "status": "blocked",
      "seen": 5850,
      "total_count": 314516,
      "stopped_at_page": 586
    },
    "Wind Archer": {
      "status": "blocked",
      "seen": 6150,
      "total_count": 246092,
      "stopped_at_page": 616
    },
    "Xenon": {
      "status": "blocked",
      "seen": 5750,
      "total_count": 326298,
      "stopped_at_page": 576
    },
    "Zero": {
      "status": "blocked",
      "seen": 5950,
      "total_count": 482477,
      "stopped_at_page": 596
    }
  }
}